setup.py
alex_mess_client.egg-info/PKG-INFO
alex_mess_client.egg-info/SOURCES.txt
alex_mess_client.egg-info/dependency_links.txt
alex_mess_client.egg-info/requires.txt
alex_mess_client.egg-info/top_level.txt
client/__init__.py
client/client.py
client/launcher.py
client/client/__init__.py
client/client/add_contact.py
client/client/database.py
client/client/del_contact.py
client/client/main_window.py
client/client/main_window_conv.py
client/client/start_dialog.py
client/client/transport.py
client/common/__init__.py
client/common/decos.py
client/common/descryptors.py
client/common/errors.py
client/common/metaclasses.py
client/common/utils.py
client/common/variables.py
client/project_logs/__init__.py
client/project_logs/configs/__init__.py
client/project_logs/configs/client_log_config.py
client/project_logs/configs/server_log_config.py
client/project_logs/logs/__init__.py
client/unit_tests/__init__.py
client/unit_tests/test_client.py
client/unit_tests/test_server.py
client/unit_tests/test_utils.py