Metadata-Version: 2.1
Name: alex-mess-client
Version: 0.0.1
Summary: my_mess_client
Home-page: UNKNOWN
Author: Alexandr Pogrebnyak
Author-email: cool.cyclon@yandex.ru
License: UNKNOWN
Platform: UNKNOWN
